fastfhir/__init__.py
fastfhir/fastapi_router.py
fastfhir/helpers.py
fastfhir/models.py
fastfhir/utlis.py
fastfhir/validation.py
fastfhir-0.2.0.dist-info/METADATA
fastfhir-0.2.0.dist-info/WHEEL
fastfhir-0.2.0.dist-info/top_level.txt
fastfhir-0.2.0.dist-info/RECORD
